{
  "url": "https://levimcg.com/",
  "requestedUrl": "https://levimcg.com/",
  "timestamp": 1619391333284,
  "ranks": {
    "hundos": 155,
    "performance": 254,
    "accessibility": 112,
    "cumulative": 148
  },
  "lighthouse": {
    "version": "7.3.0",
    "performance": 0.99,
    "accessibility": 1,
    "bestPractices": 1,
    "seo": 1,
    "total": 399
  },
  "firstContentfulPaint": 1643.652,
  "speedIndex": 1825.6226163051606,
  "largestContentfulPaint": 1643.652,
  "totalBlockingTime": 0,
  "cumulativeLayoutShift": 0.04707137044270834,
  "timeToInteractive": 1643.652,
  "maxPotentialFirstInputDelay": 16,
  "timeToFirstByte": 85.227,
  "weight": {
    "summary": "5 requests • 44 KiB",
    "total": 45045,
    "image": 0,
    "imageCount": 0,
    "script": 1393,
    "scriptCount": 1,
    "document": 2138,
    "font": 37305,
    "fontCount": 1,
    "stylesheet": 4209,
    "stylesheetCount": 2,
    "thirdParty": 39827,
    "thirdPartyCount": 3
  },
  "run": {
    "number": 2,
    "total": 3
  },
  "axe": {
    "passes": 185,
    "violations": 0
  }
}