{
  "url": "https://www.stjaer.net/",
  "requestedUrl": "https://www.stjaer.net/",
  "timestamp": 1654498291158,
  "ranks": {
    "hundos": 76,
    "performance": 215,
    "accessibility": 70,
    "cumulative": 52
  },
  "lighthouse": {
    "version": "9.6.1",
    "performance": 1,
    "accessibility": 1,
    "bestPractices": 1,
    "seo": 1,
    "total": 400
  },
  "firstContentfulPaint": 1219.998,
  "firstMeaningfulPaint": 1219.998,
  "speedIndex": 1916.2563480004492,
  "largestContentfulPaint": 1405.998,
  "totalBlockingTime": 0,
  "cumulativeLayoutShift": 0,
  "timeToInteractive": 1219.998,
  "maxPotentialFirstInputDelay": 16,
  "timeToFirstByte": 172.20799999999997,
  "weight": {
    "summary": "8 requests • 117 KiB",
    "total": 119418,
    "image": 108026,
    "imageCount": 5,
    "script": 826,
    "scriptCount": 1,
    "document": 4556,
    "font": 0,
    "fontCount": 0,
    "stylesheet": 6010,
    "stylesheetCount": 1,
    "thirdParty": 0,
    "thirdPartyCount": 0
  },
  "run": {
    "number": 3,
    "total": 3
  },
  "sidequests": {
    "-weight.total": 247,
    "+weight.total": 393,
    "-weight.document": 239,
    "+weight.document": 391,
    "-weight.script": 19,
    "+weight.script": 412,
    "-weight.image": 232,
    "+weight.image": 246,
    "-weight.font": 1,
    "+weight.font": 418,
    "+weight.fontCount": 15,
    "-timeToFirstByte": 466,
    "-totalBlockingTime": 1,
    "-largestContentfulPaint": 201
  },
  "axe": {
    "passes": 393,
    "violations": 0
  }
}