{
  "url": "https://nothingrandom.com/",
  "requestedUrl": "https://nothingrandom.com/",
  "timestamp": 1600638492422,
  "ranks": {
    "hundos": 177,
    "performance": 259,
    "accessibility": 311,
    "cumulative": 187
  },
  "lighthouse": {
    "version": "6.1.1",
    "performance": 0.99,
    "accessibility": 0.95,
    "bestPractices": 1,
    "seo": 1,
    "total": 394
  },
  "firstContentfulPaint": 1058.8780000000002,
  "speedIndex": 1976.2741846872946,
  "largestContentfulPaint": 1517.8780000000002,
  "totalBlockingTime": 207,
  "cumulativeLayoutShift": 0,
  "timeToInteractive": 2792.878,
  "maxPotentialFirstInputDelay": 183,
  "timeToFirstByte": 161.15,
  "weight": {
    "summary": "8 requests • 473 KiB",
    "total": 484801,
    "image": 196916,
    "imageCount": 1,
    "script": 22699,
    "scriptCount": 1,
    "document": 4492,
    "font": 254545,
    "fontCount": 4,
    "stylesheet": 6149,
    "stylesheetCount": 1,
    "thirdParty": 0,
    "thirdPartyCount": 0
  },
  "axe": {
    "passes": 372,
    "violations": 23
  }
}