{
  "url": "https://marcoslooten.com/",
  "requestedUrl": "https://marcoslooten.com/",
  "timestamp": 1710399322229,
  "ranks": {
    "hundos": 445,
    "performance": 252,
    "accessibility": 781,
    "cumulative": 461
  },
  "lighthouse": {
    "version": "11.6.0",
    "performance": 1,
    "accessibility": 0.92,
    "bestPractices": 1,
    "seo": 1,
    "total": 392
  },
  "firstContentfulPaint": 983.9665,
  "firstMeaningfulPaint": 983.9665,
  "speedIndex": 1435.4115136100468,
  "largestContentfulPaint": 983.9665,
  "totalBlockingTime": 14,
  "cumulativeLayoutShift": 0.03496132915307918,
  "timeToInteractive": 2467.2825000000003,
  "maxPotentialFirstInputDelay": 78,
  "timeToFirstByte": 200.231,
  "weight": {
    "summary": "14 requests • 363.0 KiB",
    "total": 371661,
    "image": 32012,
    "imageCount": 3,
    "script": 180138,
    "scriptCount": 4,
    "document": 5225,
    "font": 148092,
    "fontCount": 2,
    "stylesheet": 5932,
    "stylesheetCount": 2,
    "thirdParty": 328573,
    "thirdPartyCount": 3
  },
  "run": {
    "number": 3,
    "total": 3
  },
  "sidequests": {
    "-weight.total": 643,
    "+weight.total": 331,
    "-weight.document": 400,
    "+weight.document": 545,
    "-weight.script": 571,
    "+weight.script": 120,
    "-weight.image": 198,
    "+weight.image": 550,
    "-weight.font": 525,
    "+weight.font": 137,
    "+weight.fontCount": 14,
    "-timeToFirstByte": 709,
    "-totalBlockingTime": 29,
    "-largestContentfulPaint": 533
  },
  "axe": {
    "passes": 92,
    "violations": 16
  }
}