{
  "url": "https://everydayia.com/",
  "requestedUrl": "https://everydayia.com/",
  "timestamp": 1599425179337,
  "ranks": {
    "hundos": 141,
    "performance": 43,
    "accessibility": 243,
    "cumulative": 141
  },
  "lighthouse": {
    "version": "6.1.1",
    "performance": 1,
    "accessibility": 0.97,
    "bestPractices": 1,
    "seo": 1,
    "total": 397
  },
  "firstContentfulPaint": 916,
  "speedIndex": 1037.2145924582103,
  "largestContentfulPaint": 916,
  "totalBlockingTime": 1,
  "cumulativeLayoutShift": 0,
  "timeToInteractive": 964.5,
  "maxPotentialFirstInputDelay": 52,
  "timeToFirstByte": 83.12500000000003,
  "weight": {
    "summary": "4 requests • 146 KiB",
    "total": 148996,
    "image": 72307,
    "imageCount": 1,
    "script": 0,
    "scriptCount": 0,
    "document": 4288,
    "font": 70088,
    "fontCount": 1,
    "stylesheet": 2313,
    "stylesheetCount": 1,
    "thirdParty": 0,
    "thirdPartyCount": 0
  },
  "axe": {
    "passes": 99,
    "violations": 1
  }
}