{
  "url": "https://multilingual.lea-tortay.com/",
  "requestedUrl": "https://multilingual.lea-tortay.com/",
  "timestamp": 1643594008681,
  "ranks": {
    "hundos": 113,
    "performance": 24,
    "accessibility": 198,
    "cumulative": 83
  },
  "lighthouse": {
    "version": "9.2.0",
    "performance": 1,
    "accessibility": 1,
    "bestPractices": 1,
    "seo": 1,
    "total": 400
  },
  "firstContentfulPaint": 956.346,
  "firstMeaningfulPaint": 956.346,
  "speedIndex": 1013.4086999992072,
  "largestContentfulPaint": 956.346,
  "totalBlockingTime": 0,
  "cumulativeLayoutShift": 0,
  "timeToInteractive": 956.346,
  "maxPotentialFirstInputDelay": 16,
  "timeToFirstByte": 201.387,
  "weight": {
    "summary": "1 request • 2 KiB",
    "total": 1805,
    "image": 0,
    "imageCount": 0,
    "script": 0,
    "scriptCount": 0,
    "document": 1805,
    "font": 0,
    "fontCount": 0,
    "stylesheet": 0,
    "stylesheetCount": 0,
    "thirdParty": 0,
    "thirdPartyCount": 0
  },
  "run": {
    "number": 3,
    "total": 3
  },
  "axe": {
    "passes": 57,
    "violations": 0
  }
}