{
  "url": "https://zoepage.github.io/",
  "requestedUrl": "https://zoepage.github.io/",
  "timestamp": 1674889038506,
  "ranks": {
    "hundos": 612,
    "performance": 42,
    "accessibility": 764,
    "cumulative": 612
  },
  "lighthouse": {
    "version": "9.6.5",
    "performance": 1,
    "accessibility": 0.84,
    "bestPractices": 1,
    "seo": 0.97,
    "total": 381
  },
  "firstContentfulPaint": 902.37,
  "firstMeaningfulPaint": 902.37,
  "speedIndex": 902.37,
  "largestContentfulPaint": 902.37,
  "totalBlockingTime": 0,
  "cumulativeLayoutShift": 0,
  "timeToInteractive": 902.37,
  "maxPotentialFirstInputDelay": 16,
  "timeToFirstByte": 53.43500000000002,
  "weight": {
    "summary": "6 requests • 2,688 KiB",
    "total": 2752432,
    "image": 2746844,
    "imageCount": 3,
    "script": 0,
    "scriptCount": 0,
    "document": 2794,
    "font": 0,
    "fontCount": 0,
    "stylesheet": 2794,
    "stylesheetCount": 2,
    "thirdParty": 2746844,
    "thirdPartyCount": 3
  },
  "run": {
    "number": 2,
    "total": 3
  },
  "sidequests": {
    "-weight.total": 779,
    "+weight.total": 38,
    "-weight.document": 147,
    "+weight.document": 654,
    "-weight.script": 1,
    "+weight.script": 567,
    "-weight.image": 598,
    "+weight.image": 23,
    "-weight.font": 1,
    "+weight.font": 544,
    "+weight.fontCount": 15,
    "-timeToFirstByte": 188,
    "-totalBlockingTime": 1,
    "-largestContentfulPaint": 276
  },
  "axe": {
    "passes": 260,
    "violations": 7
  }
}