{
  "url": "https://webcomponents.club/",
  "requestedUrl": "https://webcomponents.club/",
  "timestamp": 1607908515219,
  "ranks": {
    "hundos": 217,
    "performance": 81,
    "accessibility": 21,
    "cumulative": 217
  },
  "lighthouse": {
    "version": "6.1.0",
    "performance": 1,
    "accessibility": 1,
    "bestPractices": 1,
    "seo": 0.92,
    "total": 392
  },
  "firstContentfulPaint": 1006.062,
  "speedIndex": 1261.5355639605993,
  "largestContentfulPaint": 1006.062,
  "totalBlockingTime": 44.499999999999886,
  "cumulativeLayoutShift": 0,
  "timeToInteractive": 1150.562,
  "maxPotentialFirstInputDelay": 147.9999999999999,
  "timeToFirstByte": 196.193,
  "weight": {
    "summary": "2 requests • 131 KiB",
    "total": 134441,
    "image": 125880,
    "imageCount": 1,
    "script": 0,
    "scriptCount": 0,
    "document": 8561,
    "font": 0,
    "fontCount": 0,
    "stylesheet": 0,
    "stylesheetCount": 0,
    "thirdParty": 125880,
    "thirdPartyCount": 1
  },
  "run": {
    "number": 3,
    "total": 3
  },
  "axe": {
    "passes": 554,
    "violations": 0
  }
}