{
  "url": "https://pardeletras.com/",
  "requestedUrl": "https://pardeletras.com/",
  "timestamp": 1676162574896,
  "ranks": {
    "hundos": 245,
    "performance": 394,
    "accessibility": 470,
    "cumulative": 253
  },
  "lighthouse": {
    "version": "10.0.0",
    "performance": 0.99,
    "accessibility": 1,
    "bestPractices": 1,
    "seo": 1,
    "total": 399
  },
  "firstContentfulPaint": 1642.166,
  "firstMeaningfulPaint": 1642.166,
  "speedIndex": 1674.4586400005765,
  "largestContentfulPaint": 1642.166,
  "totalBlockingTime": 0,
  "cumulativeLayoutShift": 0.000019260072159401618,
  "timeToInteractive": 1642.166,
  "maxPotentialFirstInputDelay": 16,
  "timeToFirstByte": 41.27800000000002,
  "weight": {
    "summary": "9 requests • 224 KiB",
    "total": 229319,
    "image": 3128,
    "imageCount": 3,
    "script": 0,
    "scriptCount": 0,
    "document": 2429,
    "font": 220606,
    "fontCount": 1,
    "stylesheet": 2910,
    "stylesheetCount": 3,
    "thirdParty": 223642,
    "thirdPartyCount": 4
  },
  "run": {
    "number": 2,
    "total": 3
  },
  "sidequests": {
    "-weight.total": 472,
    "+weight.total": 367,
    "-weight.document": 118,
    "+weight.document": 700,
    "-weight.script": 1,
    "+weight.script": 573,
    "-weight.image": 46,
    "+weight.image": 593,
    "-weight.font": 490,
    "+weight.font": 75,
    "+weight.fontCount": 14,
    "-timeToFirstByte": 41,
    "-totalBlockingTime": 1,
    "-largestContentfulPaint": 607
  },
  "axe": {
    "passes": 116,
    "violations": 5
  }
}