{
  "url": "https://website-29177.eventmaker.io/",
  "requestedUrl": "https://website-29177.eventmaker.io/",
  "timestamp": 1653942766146,
  "ranks": {
    "hundos": 3,
    "performance": 4,
    "accessibility": 4,
    "cumulative": 3
  },
  "lighthouse": {
    "version": "9.5.0",
    "performance": 0.3,
    "accessibility": 0.96,
    "bestPractices": 0.92,
    "seo": 0.79,
    "total": 297
  },
  "firstContentfulPaint": 7407.812000000003,
  "firstMeaningfulPaint": 7407.812000000003,
  "speedIndex": 11905.12199425468,
  "largestContentfulPaint": 15586.429000000007,
  "totalBlockingTime": 635.5,
  "cumulativeLayoutShift": 0.003973782857259115,
  "timeToInteractive": 14978.789500000004,
  "maxPotentialFirstInputDelay": 655,
  "timeToFirstByte": 226.90499999999997,
  "weight": {
    "summary": "38 requests • 3,235 KiB",
    "total": 3312241,
    "image": 2066448,
    "imageCount": 14,
    "script": 1000553,
    "scriptCount": 10,
    "document": 12936,
    "font": 158676,
    "fontCount": 5,
    "stylesheet": 73153,
    "stylesheetCount": 6,
    "thirdParty": 2172498,
    "thirdPartyCount": 28
  },
  "run": {
    "number": 2,
    "total": 3
  },
  "axe": {
    "passes": 920,
    "violations": 60
  }
}