{
  "url": "https://website-29177.eventmaker.io/",
  "requestedUrl": "https://website-29177.eventmaker.io/",
  "timestamp": 1653251597594,
  "ranks": {
    "hundos": 4,
    "performance": 3,
    "accessibility": 3,
    "cumulative": 4
  },
  "lighthouse": {
    "version": "9.5.0",
    "performance": 0.29,
    "accessibility": 0.96,
    "bestPractices": 0.92,
    "seo": 0.79,
    "total": 296
  },
  "firstContentfulPaint": 7325.426000000001,
  "firstMeaningfulPaint": 7325.426000000001,
  "speedIndex": 12493.888917706254,
  "largestContentfulPaint": 15678.943000000003,
  "totalBlockingTime": 699,
  "cumulativeLayoutShift": 0.004007504781087239,
  "timeToInteractive": 14906.797000000002,
  "maxPotentialFirstInputDelay": 879,
  "timeToFirstByte": 231.887,
  "weight": {
    "summary": "38 requests • 3,233 KiB",
    "total": 3310535,
    "image": 2066448,
    "imageCount": 14,
    "script": 998945,
    "scriptCount": 10,
    "document": 12956,
    "font": 158686,
    "fontCount": 5,
    "stylesheet": 73028,
    "stylesheetCount": 6,
    "thirdParty": 2172061,
    "thirdPartyCount": 28
  },
  "run": {
    "number": 2,
    "total": 3
  },
  "axe": {
    "passes": 920,
    "violations": 60
  }
}