{
  "url": "https://genehack.blog/",
  "requestedUrl": "https://genehack.blog/",
  "timestamp": 1676169836476,
  "ranks": {
    "hundos": 748,
    "performance": 802,
    "accessibility": 349,
    "cumulative": 746
  },
  "lighthouse": {
    "version": "10.0.0",
    "performance": 0.59,
    "accessibility": 1,
    "bestPractices": 1,
    "seo": 0.98,
    "total": 357
  },
  "firstContentfulPaint": 953.95,
  "firstMeaningfulPaint": 1019.95,
  "speedIndex": 2690.561826342293,
  "largestContentfulPaint": 15061.95,
  "totalBlockingTime": 545,
  "cumulativeLayoutShift": 0.0932813449958912,
  "timeToInteractive": 1638.95,
  "maxPotentialFirstInputDelay": 538,
  "timeToFirstByte": 136.2750000000001,
  "weight": {
    "summary": "14 requests • 2,902 KiB",
    "total": 2972129,
    "image": 2847728,
    "imageCount": 4,
    "script": 0,
    "scriptCount": 0,
    "document": 5413,
    "font": 113611,
    "fontCount": 5,
    "stylesheet": 5377,
    "stylesheetCount": 4,
    "thirdParty": 0,
    "thirdPartyCount": 0
  },
  "run": {
    "number": 2,
    "total": 3
  },
  "sidequests": {
    "-weight.total": 799,
    "+weight.total": 40,
    "-weight.document": 362,
    "+weight.document": 456,
    "-weight.script": 1,
    "+weight.script": 573,
    "-weight.image": 614,
    "+weight.image": 25,
    "-weight.font": 410,
    "+weight.font": 155,
    "+weight.fontCount": 10,
    "-timeToFirstByte": 496,
    "-totalBlockingTime": 262,
    "-largestContentfulPaint": 830
  },
  "axe": {
    "passes": 272,
    "violations": 1
  }
}