{
  "url": "https://geshov.ru/",
  "requestedUrl": "https://geshov.ru/",
  "timestamp": 1666581338429,
  "ranks": {
    "hundos": 211,
    "performance": 369,
    "accessibility": 411,
    "cumulative": 229
  },
  "lighthouse": {
    "version": "9.6.5",
    "performance": 0.99,
    "accessibility": 1,
    "bestPractices": 1,
    "seo": 1,
    "total": 399
  },
  "firstContentfulPaint": 1245.5040000000001,
  "firstMeaningfulPaint": 1245.5040000000001,
  "speedIndex": 2226.360580229147,
  "largestContentfulPaint": 2086.15,
  "totalBlockingTime": 3,
  "cumulativeLayoutShift": 0.0000358475579155816,
  "timeToInteractive": 1911.1655,
  "maxPotentialFirstInputDelay": 69,
  "timeToFirstByte": 41.70400000000001,
  "weight": {
    "summary": "13 requests • 467 KiB",
    "total": 477722,
    "image": 128154,
    "imageCount": 3,
    "script": 74176,
    "scriptCount": 3,
    "document": 49550,
    "font": 225842,
    "fontCount": 6,
    "stylesheet": 0,
    "stylesheetCount": 0,
    "thirdParty": 54884,
    "thirdPartyCount": 1
  },
  "run": {
    "number": 2,
    "total": 3
  },
  "sidequests": {
    "-weight.total": 543,
    "+weight.total": 202,
    "-weight.document": 698,
    "+weight.document": 30,
    "-weight.script": 366,
    "+weight.script": 155,
    "-weight.image": 291,
    "+weight.image": 278,
    "-weight.font": 439,
    "+weight.font": 61,
    "+weight.fontCount": 10,
    "-timeToFirstByte": 106,
    "-totalBlockingTime": 9,
    "-largestContentfulPaint": 506
  },
  "axe": {
    "passes": 220,
    "violations": 5
  }
}