{
  "url": "https://questhink.com/",
  "requestedUrl": "https://questhink.com/",
  "timestamp": 1606693555768,
  "ranks": {
    "hundos": 293,
    "performance": 259,
    "accessibility": 357,
    "cumulative": 294
  },
  "lighthouse": {
    "version": "6.4.1",
    "performance": 0.98,
    "accessibility": 0.93,
    "bestPractices": 0.93,
    "seo": 1,
    "total": 384
  },
  "firstContentfulPaint": 1627.4900000000002,
  "speedIndex": 1627.4900000000002,
  "largestContentfulPaint": 1952.8450000000003,
  "totalBlockingTime": 5,
  "cumulativeLayoutShift": 0.0021077473958333332,
  "timeToInteractive": 3087.677,
  "maxPotentialFirstInputDelay": 55,
  "timeToFirstByte": 108.11399999999998,
  "weight": {
    "summary": "10 requests • 115 KiB",
    "total": 118191,
    "image": 0,
    "imageCount": 0,
    "script": 59464,
    "scriptCount": 3,
    "document": 2137,
    "font": 51293,
    "fontCount": 3,
    "stylesheet": 5093,
    "stylesheetCount": 2,
    "thirdParty": 111113,
    "thirdPartyCount": 7
  },
  "run": {
    "number": 2,
    "total": 3
  },
  "axe": {
    "passes": 54,
    "violations": 4
  }
}