{
  "url": "https://microblog.hankchizljaw.com/archive/0/",
  "requestedUrl": "https://microblog.hankchizljaw.com/",
  "timestamp": 1612135383550,
  "ranks": {
    "hundos": 324,
    "performance": 288,
    "accessibility": 83,
    "cumulative": 324
  },
  "lighthouse": {
    "version": "6.5.0",
    "performance": 0.98,
    "accessibility": 1,
    "bestPractices": 1,
    "seo": 0.83,
    "total": 381
  },
  "firstContentfulPaint": 1638.9180000000003,
  "speedIndex": 3179.4667320173503,
  "largestContentfulPaint": 1638.9180000000003,
  "totalBlockingTime": 0,
  "cumulativeLayoutShift": 0.005342610677083333,
  "timeToInteractive": 1638.9180000000003,
  "maxPotentialFirstInputDelay": 16,
  "timeToFirstByte": 75.244,
  "weight": {
    "summary": "6 requests • 42 KiB",
    "total": 42539,
    "image": 11940,
    "imageCount": 1,
    "script": 0,
    "scriptCount": 0,
    "document": 4710,
    "font": 24684,
    "fontCount": 1,
    "stylesheet": 914,
    "stylesheetCount": 1,
    "thirdParty": 914,
    "thirdPartyCount": 1
  },
  "run": {
    "number": 2,
    "total": 3
  },
  "axe": {
    "passes": 225,
    "violations": 0
  }
}