{
  "url": "https://www.belter.io/",
  "requestedUrl": "https://www.belter.io/",
  "timestamp": 1663536088663,
  "ranks": {
    "hundos": 316,
    "performance": 112,
    "accessibility": 495,
    "cumulative": 314
  },
  "lighthouse": {
    "version": "9.6.5",
    "performance": 1,
    "accessibility": 0.97,
    "bestPractices": 1,
    "seo": 0.98,
    "total": 395
  },
  "firstContentfulPaint": 969.442,
  "firstMeaningfulPaint": 969.442,
  "speedIndex": 1046.8053720024263,
  "largestContentfulPaint": 969.442,
  "totalBlockingTime": 0,
  "cumulativeLayoutShift": 0,
  "timeToInteractive": 969.442,
  "maxPotentialFirstInputDelay": 16,
  "timeToFirstByte": 41.28899999999999,
  "weight": {
    "summary": "3 requests • 21 KiB",
    "total": 21320,
    "image": 13331,
    "imageCount": 1,
    "script": 714,
    "scriptCount": 1,
    "document": 7275,
    "font": 0,
    "fontCount": 0,
    "stylesheet": 0,
    "stylesheetCount": 0,
    "thirdParty": 13331,
    "thirdPartyCount": 1
  },
  "run": {
    "number": 1,
    "total": 3
  },
  "sidequests": {
    "-weight.total": 87,
    "+weight.total": 648,
    "-weight.document": 414,
    "+weight.document": 307,
    "-weight.script": 14,
    "+weight.script": 484,
    "-weight.image": 93,
    "+weight.image": 466,
    "-weight.font": 1,
    "+weight.font": 491,
    "+weight.fontCount": 16,
    "-timeToFirstByte": 78,
    "-totalBlockingTime": 1,
    "-largestContentfulPaint": 282
  },
  "axe": {
    "passes": 479,
    "violations": 2
  }
}