{
  "url": "https://dogsof.dev/",
  "requestedUrl": "https://dogsof.dev/",
  "timestamp": 1681360557017,
  "ranks": {
    "hundos": 31,
    "performance": 181,
    "accessibility": 61,
    "cumulative": 20
  },
  "lighthouse": {
    "version": "10.1.0",
    "performance": 1,
    "accessibility": 1,
    "bestPractices": 1,
    "seo": 1,
    "total": 400
  },
  "firstContentfulPaint": 944.742,
  "firstMeaningfulPaint": 944.742,
  "speedIndex": 1189.6276919998559,
  "largestContentfulPaint": 1334.742,
  "totalBlockingTime": 0,
  "cumulativeLayoutShift": 0.00260882115785911,
  "timeToInteractive": 944.742,
  "maxPotentialFirstInputDelay": 16,
  "timeToFirstByte": 87.56999999999996,
  "weight": {
    "summary": "12 requests • 165 KiB",
    "total": 168908,
    "image": 139322,
    "imageCount": 9,
    "script": 0,
    "scriptCount": 0,
    "document": 3703,
    "font": 25883,
    "fontCount": 2,
    "stylesheet": 0,
    "stylesheetCount": 0,
    "thirdParty": 0,
    "thirdPartyCount": 0
  },
  "run": {
    "number": 3,
    "total": 3
  },
  "sidequests": {
    "-weight.total": 402,
    "+weight.total": 465,
    "-weight.document": 238,
    "+weight.document": 608,
    "-weight.script": 1,
    "+weight.script": 611,
    "-weight.image": 363,
    "+weight.image": 306,
    "-weight.font": 91,
    "+weight.font": 488,
    "+weight.fontCount": 15,
    "-timeToFirstByte": 386,
    "-totalBlockingTime": 1,
    "-largestContentfulPaint": 410
  },
  "axe": {
    "passes": 425,
    "violations": 0
  }
}