{
  "url": "https://divriots.com/",
  "requestedUrl": "https://divriots.com/",
  "timestamp": 1681331984293,
  "ranks": {
    "hundos": 503,
    "performance": 528,
    "accessibility": 37,
    "cumulative": 502
  },
  "lighthouse": {
    "version": "10.1.0",
    "performance": 0.96,
    "accessibility": 1,
    "bestPractices": 0.92,
    "seo": 1,
    "total": 388
  },
  "firstContentfulPaint": 890.53,
  "firstMeaningfulPaint": 890.53,
  "speedIndex": 890.53,
  "largestContentfulPaint": 2569.5299999999997,
  "totalBlockingTime": 114.5,
  "cumulativeLayoutShift": 0.004762627648024428,
  "timeToInteractive": 1055.03,
  "maxPotentialFirstInputDelay": 169,
  "timeToFirstByte": 13.936000000000007,
  "weight": {
    "summary": "23 requests • 245 KiB",
    "total": 250844,
    "image": 131920,
    "imageCount": 12,
    "script": 3934,
    "scriptCount": 3,
    "document": 4948,
    "font": 105797,
    "fontCount": 2,
    "stylesheet": 4245,
    "stylesheetCount": 5,
    "thirdParty": 18311,
    "thirdPartyCount": 3
  },
  "run": {
    "number": 1,
    "total": 3
  },
  "sidequests": {
    "-weight.total": 506,
    "+weight.total": 361,
    "-weight.document": 335,
    "+weight.document": 511,
    "-weight.script": 145,
    "+weight.script": 466,
    "-weight.image": 352,
    "+weight.image": 317,
    "-weight.font": 407,
    "+weight.font": 172,
    "+weight.fontCount": 15,
    "-timeToFirstByte": 3,
    "-totalBlockingTime": 131,
    "-largestContentfulPaint": 696
  },
  "axe": {
    "passes": 596,
    "violations": 0
  }
}