{
  "url": "https://bnijenhuis.nl/",
  "requestedUrl": "https://bnijenhuis.nl/",
  "timestamp": 1643577897950,
  "ranks": {
    "hundos": 177,
    "performance": 321,
    "accessibility": 165,
    "cumulative": 170
  },
  "lighthouse": {
    "version": "9.2.0",
    "performance": 0.98,
    "accessibility": 1,
    "bestPractices": 1,
    "seo": 1,
    "total": 398
  },
  "firstContentfulPaint": 801.367,
  "firstMeaningfulPaint": 801.367,
  "speedIndex": 3877.913342000216,
  "largestContentfulPaint": 801.367,
  "totalBlockingTime": 61.5,
  "cumulativeLayoutShift": 0.0005851249694824219,
  "timeToInteractive": 912.867,
  "maxPotentialFirstInputDelay": 131,
  "timeToFirstByte": 119.8760000000002,
  "weight": {
    "summary": "5 requests • 81 KiB",
    "total": 83017,
    "image": 0,
    "imageCount": 0,
    "script": 20182,
    "scriptCount": 1,
    "document": 5826,
    "font": 56103,
    "fontCount": 1,
    "stylesheet": 906,
    "stylesheetCount": 1,
    "thirdParty": 0,
    "thirdPartyCount": 0
  },
  "run": {
    "number": 1,
    "total": 3
  },
  "axe": {
    "passes": 134,
    "violations": 0
  }
}