{
  "url": "https://www.industrialempathy.com/",
  "requestedUrl": "https://www.industrialempathy.com/",
  "timestamp": 1600634972633,
  "ranks": {
    "hundos": 10,
    "performance": 206,
    "accessibility": 102,
    "cumulative": 7
  },
  "lighthouse": {
    "version": "6.1.1",
    "performance": 1,
    "accessibility": 1,
    "bestPractices": 1,
    "seo": 1,
    "total": 400
  },
  "firstContentfulPaint": 970.5020000000001,
  "speedIndex": 1948.3712274450713,
  "largestContentfulPaint": 970.5020000000001,
  "totalBlockingTime": 66.99999999999989,
  "cumulativeLayoutShift": 0.0037379964192708333,
  "timeToInteractive": 1087.502,
  "maxPotentialFirstInputDelay": 123.99999999999989,
  "timeToFirstByte": 56.56900000000002,
  "weight": {
    "summary": "9 requests • 544 KiB",
    "total": 557103,
    "image": 0,
    "imageCount": 0,
    "script": 19411,
    "scriptCount": 2,
    "document": 3015,
    "font": 534561,
    "fontCount": 5,
    "stylesheet": 0,
    "stylesheetCount": 0,
    "thirdParty": 0,
    "thirdPartyCount": 0
  },
  "axe": {
    "passes": 154,
    "violations": 0
  }
}