{
  "url": "https://books.thedixons.net/",
  "requestedUrl": "https://books.thedixons.net/",
  "timestamp": 1616981100655,
  "ranks": {
    "hundos": 279,
    "performance": 351,
    "accessibility": 13,
    "cumulative": 276
  },
  "lighthouse": {
    "version": "7.3.0",
    "performance": 0.95,
    "accessibility": 1,
    "bestPractices": 0.93,
    "seo": 1,
    "total": 388
  },
  "firstContentfulPaint": 1007,
  "speedIndex": 2525.6283994208916,
  "largestContentfulPaint": 1019,
  "totalBlockingTime": 0,
  "cumulativeLayoutShift": 0.664702150132921,
  "timeToInteractive": 1019,
  "maxPotentialFirstInputDelay": 24,
  "timeToFirstByte": 163.41699999999992,
  "weight": {
    "summary": "2 requests • 25 KiB",
    "total": 25226,
    "image": 8461,
    "imageCount": 1,
    "script": 0,
    "scriptCount": 0,
    "document": 16765,
    "font": 0,
    "fontCount": 0,
    "stylesheet": 0,
    "stylesheetCount": 0,
    "thirdParty": 0,
    "thirdPartyCount": 0
  },
  "run": {
    "number": 2,
    "total": 3
  },
  "axe": {
    "passes": 783,
    "violations": 0
  }
}