{
  "url": "https://www.jpkc.com/",
  "requestedUrl": "https://www.jpkc.com/",
  "timestamp": 1607903373867,
  "ranks": {
    "hundos": 80,
    "performance": 133,
    "accessibility": 11,
    "cumulative": 59
  },
  "lighthouse": {
    "version": "6.1.0",
    "performance": 1,
    "accessibility": 1,
    "bestPractices": 1,
    "seo": 1,
    "total": 400
  },
  "firstContentfulPaint": 1055.591,
  "speedIndex": 1527.8790687784704,
  "largestContentfulPaint": 1096.091,
  "totalBlockingTime": 25.5,
  "cumulativeLayoutShift": 0,
  "timeToInteractive": 1131.091,
  "maxPotentialFirstInputDelay": 81,
  "timeToFirstByte": 176.26800000000003,
  "weight": {
    "summary": "3 requests • 34 KiB",
    "total": 35158,
    "image": 11768,
    "imageCount": 2,
    "script": 0,
    "scriptCount": 0,
    "document": 23390,
    "font": 0,
    "fontCount": 0,
    "stylesheet": 0,
    "stylesheetCount": 0,
    "thirdParty": 0,
    "thirdPartyCount": 0
  },
  "run": {
    "number": 2,
    "total": 3
  },
  "axe": {
    "passes": 1019,
    "violations": 0
  }
}