{
  "url": "https://hebrewtransliteration.app/",
  "requestedUrl": "https://hebrewtransliteration.app/",
  "timestamp": 1710394372560,
  "ranks": {
    "hundos": 666,
    "performance": 587,
    "accessibility": 895,
    "cumulative": 666
  },
  "lighthouse": {
    "version": "11.6.0",
    "performance": 0.96,
    "accessibility": 0.84,
    "bestPractices": 1,
    "seo": 1,
    "total": 380
  },
  "firstContentfulPaint": 1976.1979999999999,
  "firstMeaningfulPaint": 2197.9885,
  "speedIndex": 2188.368040239111,
  "largestContentfulPaint": 2419.779,
  "totalBlockingTime": 80.5,
  "cumulativeLayoutShift": 0.006406282213106716,
  "timeToInteractive": 2929.5165,
  "maxPotentialFirstInputDelay": 116,
  "timeToFirstByte": 288.685,
  "weight": {
    "summary": "14 requests • 259.2 KiB",
    "total": 265417,
    "image": 15693,
    "imageCount": 3,
    "script": 195568,
    "scriptCount": 6,
    "document": 7068,
    "font": 0,
    "fontCount": 0,
    "stylesheet": 46829,
    "stylesheetCount": 2,
    "thirdParty": 215973,
    "thirdPartyCount": 3
  },
  "run": {
    "number": 3,
    "total": 3
  },
  "sidequests": {
    "-weight.total": 558,
    "+weight.total": 416,
    "-weight.document": 534,
    "+weight.document": 411,
    "-weight.script": 585,
    "+weight.script": 106,
    "-weight.image": 137,
    "+weight.image": 611,
    "-weight.font": 1,
    "+weight.font": 662,
    "+weight.fontCount": 16,
    "-timeToFirstByte": 797,
    "-totalBlockingTime": 127,
    "-largestContentfulPaint": 755
  },
  "axe": {
    "passes": 586,
    "violations": 12
  }
}