{
  "url": "https://cw2architects.com/",
  "requestedUrl": "https://cw2architects.com/",
  "timestamp": 1596498570347,
  "ranks": {
    "hundos": 267,
    "performance": 301,
    "accessibility": 241,
    "cumulative": 267
  },
  "lighthouse": {
    "version": "6.1.1",
    "performance": 0.86,
    "accessibility": 0.95,
    "bestPractices": 1,
    "seo": 0.92,
    "total": 373
  },
  "firstContentfulPaint": 1779.9589999999998,
  "speedIndex": 2208.4980220222224,
  "largestContentfulPaint": 4060.425,
  "totalBlockingTime": 2.5,
  "cumulativeLayoutShift": 0,
  "timeToInteractive": 2889.6255,
  "maxPotentialFirstInputDelay": 55,
  "timeToFirstByte": 125.76999999999998,
  "weight": {
    "summary": "20 requests • 589 KiB",
    "total": 603285,
    "image": 507458,
    "imageCount": 12,
    "script": 53551,
    "scriptCount": 3,
    "document": 5367,
    "font": 27419,
    "fontCount": 2,
    "stylesheet": 9490,
    "stylesheetCount": 2,
    "thirdParty": 574819,
    "thirdPartyCount": 13
  },
  "axe": {
    "passes": 235,
    "violations": 4
  }
}