{
  "url": "https://davidkistauri.ru/",
  "requestedUrl": "https://davidkistauri.ru/",
  "timestamp": 1596498602142,
  "ranks": {
    "hundos": 162,
    "performance": 26,
    "accessibility": 221,
    "cumulative": 165
  },
  "lighthouse": {
    "version": "6.1.1",
    "performance": 1,
    "accessibility": 0.96,
    "bestPractices": 1,
    "seo": 0.95,
    "total": 391
  },
  "firstContentfulPaint": 863.639,
  "speedIndex": 994.8865099490645,
  "largestContentfulPaint": 1251.6390000000001,
  "totalBlockingTime": 108.50000000000006,
  "cumulativeLayoutShift": 0,
  "timeToInteractive": 1069.1390000000001,
  "maxPotentialFirstInputDelay": 210,
  "timeToFirstByte": 50.43699999999998,
  "weight": {
    "summary": "9 requests • 65 KiB",
    "total": 66215,
    "image": 1172,
    "imageCount": 2,
    "script": 0,
    "scriptCount": 0,
    "document": 5427,
    "font": 56825,
    "fontCount": 3,
    "stylesheet": 2791,
    "stylesheetCount": 3,
    "thirdParty": 0,
    "thirdPartyCount": 0
  },
  "axe": {
    "passes": 278,
    "violations": 2
  }
}