{
  "url": "https://www.artofmusic.lu/en/",
  "requestedUrl": "https://www.artofmusic.lu/",
  "timestamp": 1633976883025,
  "ranks": {
    "hundos": 207,
    "performance": 364,
    "accessibility": 136,
    "cumulative": 204
  },
  "lighthouse": {
    "version": "8.5.1",
    "performance": 0.96,
    "accessibility": 1,
    "bestPractices": 1,
    "seo": 1,
    "total": 396
  },
  "firstContentfulPaint": 1010.867,
  "firstMeaningfulPaint": 1010.867,
  "speedIndex": 2330.20697413126,
  "largestContentfulPaint": 1010.867,
  "totalBlockingTime": 74,
  "cumulativeLayoutShift": 0.15155166200796766,
  "timeToInteractive": 2414.563,
  "maxPotentialFirstInputDelay": 107,
  "timeToFirstByte": 171.26399999999998,
  "weight": {
    "summary": "9 requests • 421 KiB",
    "total": 431506,
    "image": 87425,
    "imageCount": 2,
    "script": 54966,
    "scriptCount": 1,
    "document": 5027,
    "font": 279179,
    "fontCount": 2,
    "stylesheet": 4551,
    "stylesheetCount": 1,
    "thirdParty": 54966,
    "thirdPartyCount": 1
  },
  "run": {
    "number": 3,
    "total": 3
  },
  "axe": {
    "passes": 171,
    "violations": 0
  }
}