{
  "url": "https://hamatti.org/",
  "requestedUrl": "https://hamatti.org/",
  "timestamp": 1600634752943,
  "ranks": {
    "hundos": 330,
    "performance": 368,
    "accessibility": 201,
    "cumulative": 331
  },
  "lighthouse": {
    "version": "6.1.1",
    "performance": 0.85,
    "accessibility": 1,
    "bestPractices": 0.92,
    "seo": 0.97,
    "total": 374
  },
  "firstContentfulPaint": 1913.842,
  "speedIndex": 2661.286140010046,
  "largestContentfulPaint": 3915.38,
  "totalBlockingTime": 179.99999999999977,
  "cumulativeLayoutShift": 0,
  "timeToInteractive": 3817.1985,
  "maxPotentialFirstInputDelay": 409.99999999999955,
  "timeToFirstByte": 307.601,
  "weight": {
    "summary": "23 requests • 2,177 KiB",
    "total": 2229711,
    "image": 850890,
    "imageCount": 14,
    "script": 141550,
    "scriptCount": 1,
    "document": 9294,
    "font": 12399,
    "fontCount": 1,
    "stylesheet": 14426,
    "stylesheetCount": 5,
    "thirdParty": 1216365,
    "thirdPartyCount": 4
  },
  "axe": {
    "passes": 533,
    "violations": 3
  }
}