{
  "url": "https://www.johnbiggins.net/",
  "requestedUrl": "https://www.johnbiggins.net/",
  "timestamp": 1674888938259,
  "ranks": {
    "hundos": 195,
    "performance": 176,
    "accessibility": 258,
    "cumulative": 144
  },
  "lighthouse": {
    "version": "9.6.5",
    "performance": 1,
    "accessibility": 1,
    "bestPractices": 1,
    "seo": 1,
    "total": 400
  },
  "firstContentfulPaint": 1076.39,
  "firstMeaningfulPaint": 1076.39,
  "speedIndex": 1224.3426879976769,
  "largestContentfulPaint": 1076.39,
  "totalBlockingTime": 0,
  "cumulativeLayoutShift": 0,
  "timeToInteractive": 1076.39,
  "maxPotentialFirstInputDelay": 16,
  "timeToFirstByte": 324.29,
  "weight": {
    "summary": "1 request • 3 KiB",
    "total": 3138,
    "image": 0,
    "imageCount": 0,
    "script": 0,
    "scriptCount": 0,
    "document": 3138,
    "font": 0,
    "fontCount": 0,
    "stylesheet": 0,
    "stylesheetCount": 0,
    "thirdParty": 0,
    "thirdPartyCount": 0
  },
  "run": {
    "number": 2,
    "total": 3
  },
  "sidequests": {
    "-weight.total": 12,
    "+weight.total": 805,
    "-weight.document": 178,
    "+weight.document": 623,
    "-weight.script": 1,
    "+weight.script": 567,
    "-weight.image": 1,
    "+weight.image": 621,
    "-weight.font": 1,
    "+weight.font": 544,
    "+weight.fontCount": 15,
    "-timeToFirstByte": 698,
    "-totalBlockingTime": 1,
    "-largestContentfulPaint": 390
  },
  "axe": {
    "passes": 132,
    "violations": 0
  }
}