{
  "url": "https://screen-read.com/",
  "requestedUrl": "https://screen-read.com/",
  "timestamp": 1616981099849,
  "ranks": {
    "hundos": 384,
    "performance": 169,
    "accessibility": 431,
    "cumulative": 381
  },
  "lighthouse": {
    "version": "7.3.0",
    "performance": 1,
    "accessibility": 0.85,
    "bestPractices": 1,
    "seo": 0.87,
    "total": 372
  },
  "firstContentfulPaint": 1085.999,
  "speedIndex": 1994.4916778417578,
  "largestContentfulPaint": 1131.999,
  "totalBlockingTime": 0,
  "cumulativeLayoutShift": 0,
  "timeToInteractive": 1085.999,
  "maxPotentialFirstInputDelay": 16,
  "timeToFirstByte": 212.09199999999998,
  "weight": {
    "summary": "5 requests • 16 KiB",
    "total": 16016,
    "image": 11184,
    "imageCount": 1,
    "script": 2173,
    "scriptCount": 2,
    "document": 1613,
    "font": 0,
    "fontCount": 0,
    "stylesheet": 1046,
    "stylesheetCount": 1,
    "thirdParty": 0,
    "thirdPartyCount": 0
  },
  "run": {
    "number": 1,
    "total": 3
  },
  "axe": {
    "passes": 110,
    "violations": 8
  }
}