{
  "url": "https://artbarcelonamag.com/",
  "requestedUrl": "https://artbarcelonamag.com/",
  "timestamp": 1663559179766,
  "ranks": {
    "hundos": 323,
    "performance": 471,
    "accessibility": 387,
    "cumulative": 331
  },
  "lighthouse": {
    "version": "9.6.5",
    "performance": 0.96,
    "accessibility": 1,
    "bestPractices": 1,
    "seo": 0.98,
    "total": 394
  },
  "firstContentfulPaint": 1891.417,
  "firstMeaningfulPaint": 4478.846,
  "speedIndex": 2288.5262740156822,
  "largestContentfulPaint": 2112.17,
  "totalBlockingTime": 3,
  "cumulativeLayoutShift": 0.0026637013753255208,
  "timeToInteractive": 4478.846,
  "maxPotentialFirstInputDelay": 53,
  "timeToFirstByte": 53.846000000000004,
  "weight": {
    "summary": "20 requests • 1,782 KiB",
    "total": 1824928,
    "image": 751053,
    "imageCount": 13,
    "script": 32847,
    "scriptCount": 2,
    "document": 2534,
    "font": 1032047,
    "fontCount": 2,
    "stylesheet": 6447,
    "stylesheetCount": 2,
    "thirdParty": 1062024,
    "thirdPartyCount": 4
  },
  "run": {
    "number": 3,
    "total": 3
  },
  "sidequests": {
    "-weight.total": 678,
    "+weight.total": 57,
    "-weight.document": 116,
    "+weight.document": 605,
    "-weight.script": 275,
    "+weight.script": 223,
    "-weight.image": 479,
    "+weight.image": 80,
    "-weight.font": 489,
    "+weight.font": 2,
    "+weight.fontCount": 14,
    "-timeToFirstByte": 251,
    "-totalBlockingTime": 7,
    "-largestContentfulPaint": 139
  },
  "axe": {
    "passes": 281,
    "violations": 4
  }
}