{
  "url": "https://www.dandevri.es/",
  "requestedUrl": "https://www.dandevri.es/",
  "timestamp": 1654497179557,
  "ranks": {
    "hundos": 395,
    "performance": 529,
    "accessibility": 283,
    "cumulative": 393
  },
  "lighthouse": {
    "version": "9.6.1",
    "performance": 0.88,
    "accessibility": 1,
    "bestPractices": 1,
    "seo": 1,
    "total": 388
  },
  "firstContentfulPaint": 2345.004,
  "firstMeaningfulPaint": 2345.004,
  "speedIndex": 6388.5169720036665,
  "largestContentfulPaint": 2645.004,
  "totalBlockingTime": 0,
  "cumulativeLayoutShift": 0,
  "timeToInteractive": 2345.004,
  "maxPotentialFirstInputDelay": 16,
  "timeToFirstByte": 36.702999999999975,
  "weight": {
    "summary": "10 requests • 184 KiB",
    "total": 188265,
    "image": 21811,
    "imageCount": 3,
    "script": 43090,
    "scriptCount": 2,
    "document": 3215,
    "font": 35061,
    "fontCount": 2,
    "stylesheet": 85088,
    "stylesheetCount": 2,
    "thirdParty": 185050,
    "thirdPartyCount": 9
  },
  "run": {
    "number": 3,
    "total": 3
  },
  "sidequests": {
    "-weight.total": 331,
    "+weight.total": 309,
    "-weight.document": 149,
    "+weight.document": 481,
    "-weight.script": 254,
    "+weight.script": 177,
    "-weight.image": 114,
    "+weight.image": 364,
    "-weight.font": 118,
    "+weight.font": 300,
    "+weight.fontCount": 13,
    "-timeToFirstByte": 43,
    "-totalBlockingTime": 1,
    "-largestContentfulPaint": 371
  },
  "axe": {
    "passes": 192,
    "violations": 1
  }
}