{
  "url": "https://cats-in-residence.org/",
  "requestedUrl": "https://cats-in-residence.org/",
  "timestamp": 1681335825931,
  "ranks": {
    "hundos": 241,
    "performance": 370,
    "accessibility": 120,
    "cumulative": 230
  },
  "lighthouse": {
    "version": "10.1.0",
    "performance": 0.99,
    "accessibility": 1,
    "bestPractices": 1,
    "seo": 1,
    "total": 399
  },
  "firstContentfulPaint": 1146.341,
  "firstMeaningfulPaint": 1146.341,
  "speedIndex": 1410.4330260001511,
  "largestContentfulPaint": 2089.5609999999997,
  "totalBlockingTime": 0,
  "cumulativeLayoutShift": 0.03145623040104688,
  "timeToInteractive": 1146.341,
  "maxPotentialFirstInputDelay": 16,
  "timeToFirstByte": 226.85299999999998,
  "weight": {
    "summary": "9 requests • 156 KiB",
    "total": 159365,
    "image": 89949,
    "imageCount": 6,
    "script": 1678,
    "scriptCount": 1,
    "document": 5215,
    "font": 62523,
    "fontCount": 1,
    "stylesheet": 0,
    "stylesheetCount": 0,
    "thirdParty": 91126,
    "thirdPartyCount": 6
  },
  "run": {
    "number": 1,
    "total": 3
  },
  "sidequests": {
    "-weight.total": 389,
    "+weight.total": 478,
    "-weight.document": 354,
    "+weight.document": 492,
    "-weight.script": 84,
    "+weight.script": 527,
    "-weight.image": 300,
    "+weight.image": 369,
    "-weight.font": 289,
    "+weight.font": 290,
    "+weight.fontCount": 16,
    "-timeToFirstByte": 683,
    "-totalBlockingTime": 1,
    "-largestContentfulPaint": 631
  },
  "axe": {
    "passes": 296,
    "violations": 0
  }
}