{
  "url": "https://alienlebarge.ch/",
  "requestedUrl": "https://alienlebarge.ch/",
  "timestamp": 1681352058439,
  "ranks": {
    "hundos": 704,
    "performance": 745,
    "accessibility": 590,
    "cumulative": 705
  },
  "lighthouse": {
    "version": "10.1.0",
    "performance": 0.8,
    "accessibility": 0.97,
    "bestPractices": 0.92,
    "seo": 1,
    "total": 369
  },
  "firstContentfulPaint": 1986.25,
  "firstMeaningfulPaint": 1986.25,
  "speedIndex": 6936.301616588834,
  "largestContentfulPaint": 1986.25,
  "totalBlockingTime": 431.5,
  "cumulativeLayoutShift": 0.038436220502702526,
  "timeToInteractive": 12926.327000000001,
  "maxPotentialFirstInputDelay": 189,
  "timeToFirstByte": 61.76600000000002,
  "weight": {
    "summary": "32 requests • 2,011 KiB",
    "total": 2058763,
    "image": 444149,
    "imageCount": 10,
    "script": 987830,
    "scriptCount": 7,
    "document": 43952,
    "font": 470804,
    "fontCount": 4,
    "stylesheet": 80428,
    "stylesheetCount": 3,
    "thirdParty": 1600249,
    "thirdPartyCount": 28
  },
  "run": {
    "number": 3,
    "total": 3
  },
  "sidequests": {
    "-weight.total": 810,
    "+weight.total": 57,
    "-weight.document": 801,
    "+weight.document": 45,
    "-weight.script": 599,
    "+weight.script": 12,
    "-weight.image": 523,
    "+weight.image": 146,
    "-weight.font": 559,
    "+weight.font": 20,
    "+weight.fontCount": 13,
    "-timeToFirstByte": 267,
    "-totalBlockingTime": 182,
    "-largestContentfulPaint": 601
  },
  "axe": {
    "passes": 701,
    "violations": 3
  }
}