{
  "url": "https://birkscinema.co.uk/",
  "requestedUrl": "https://birkscinema.co.uk/",
  "timestamp": 1663552132878,
  "ranks": {
    "hundos": 194,
    "performance": 319,
    "accessibility": 18,
    "cumulative": 193
  },
  "lighthouse": {
    "version": "9.6.5",
    "performance": 0.99,
    "accessibility": 1,
    "bestPractices": 1,
    "seo": 1,
    "total": 399
  },
  "firstContentfulPaint": 1276.045,
  "firstMeaningfulPaint": 1276.045,
  "speedIndex": 1276.045,
  "largestContentfulPaint": 1981.493,
  "totalBlockingTime": 13.5,
  "cumulativeLayoutShift": 0.003204756392372979,
  "timeToInteractive": 1628.769,
  "maxPotentialFirstInputDelay": 77,
  "timeToFirstByte": 98.57900000000001,
  "weight": {
    "summary": "22 requests • 307 KiB",
    "total": 314579,
    "image": 227304,
    "imageCount": 16,
    "script": 15223,
    "scriptCount": 2,
    "document": 17456,
    "font": 46708,
    "fontCount": 2,
    "stylesheet": 7888,
    "stylesheetCount": 1,
    "thirdParty": 1311,
    "thirdPartyCount": 1
  },
  "run": {
    "number": 3,
    "total": 3
  },
  "sidequests": {
    "-weight.total": 467,
    "+weight.total": 268,
    "-weight.document": 608,
    "+weight.document": 113,
    "-weight.script": 225,
    "+weight.script": 273,
    "-weight.image": 355,
    "+weight.image": 204,
    "-weight.font": 186,
    "+weight.font": 305,
    "+weight.fontCount": 14,
    "-timeToFirstByte": 407,
    "-totalBlockingTime": 30,
    "-largestContentfulPaint": 130
  },
  "axe": {
    "passes": 974,
    "violations": 0
  }
}