{
  "url": "https://perthshiregravel.com/",
  "requestedUrl": "https://perthshiregravel.com/",
  "timestamp": 1666584621708,
  "ranks": {
    "hundos": 200,
    "performance": 326,
    "accessibility": 436,
    "cumulative": 231
  },
  "lighthouse": {
    "version": "9.6.5",
    "performance": 0.99,
    "accessibility": 1,
    "bestPractices": 1,
    "seo": 1,
    "total": 399
  },
  "firstContentfulPaint": 1168.779,
  "firstMeaningfulPaint": 1168.779,
  "speedIndex": 1271.9813538629485,
  "largestContentfulPaint": 1877.792,
  "totalBlockingTime": 6,
  "cumulativeLayoutShift": 0.0037202962239583333,
  "timeToInteractive": 1523.2855,
  "maxPotentialFirstInputDelay": 62,
  "timeToFirstByte": 62.97200000000001,
  "weight": {
    "summary": "14 requests • 356 KiB",
    "total": 364553,
    "image": 332868,
    "imageCount": 11,
    "script": 1301,
    "scriptCount": 1,
    "document": 16887,
    "font": 13497,
    "fontCount": 1,
    "stylesheet": 0,
    "stylesheetCount": 0,
    "thirdParty": 1301,
    "thirdPartyCount": 1
  },
  "run": {
    "number": 2,
    "total": 3
  },
  "sidequests": {
    "-weight.total": 499,
    "+weight.total": 246,
    "-weight.document": 607,
    "+weight.document": 121,
    "-weight.script": 53,
    "+weight.script": 468,
    "-weight.image": 401,
    "+weight.image": 168,
    "-weight.font": 27,
    "+weight.font": 473,
    "+weight.fontCount": 15,
    "-timeToFirstByte": 326,
    "-totalBlockingTime": 18,
    "-largestContentfulPaint": 445
  },
  "axe": {
    "passes": 1064,
    "violations": 9
  }
}