{
  "url": "https://yatil.net/",
  "requestedUrl": "https://yatil.net/",
  "timestamp": 1601843209332,
  "ranks": {
    "hundos": 363,
    "performance": 392,
    "accessibility": 57,
    "cumulative": 363
  },
  "lighthouse": {
    "version": "6.1.1",
    "performance": 0.74,
    "accessibility": 1,
    "bestPractices": 0.92,
    "seo": 0.96,
    "total": 362
  },
  "firstContentfulPaint": 884.3500000000001,
  "speedIndex": 3743.0077730014473,
  "largestContentfulPaint": 4701.0380000000005,
  "totalBlockingTime": 152,
  "cumulativeLayoutShift": 0.48080452473958335,
  "timeToInteractive": 4516.384,
  "maxPotentialFirstInputDelay": 128,
  "timeToFirstByte": 161.85300000000007,
  "weight": {
    "summary": "5 requests • 615 KiB",
    "total": 630012,
    "image": 15069,
    "imageCount": 1,
    "script": 82710,
    "scriptCount": 1,
    "document": 2814,
    "font": 524252,
    "fontCount": 1,
    "stylesheet": 5167,
    "stylesheetCount": 1,
    "thirdParty": 0,
    "thirdPartyCount": 0
  },
  "axe": {
    "passes": 253,
    "violations": 0
  }
}