{
  "url": "https://horseracingdatasets.com/",
  "requestedUrl": "https://horseracingdatasets.com/",
  "timestamp": 1663536198784,
  "ranks": {
    "hundos": 65,
    "performance": 172,
    "accessibility": 155,
    "cumulative": 41
  },
  "lighthouse": {
    "version": "9.6.5",
    "performance": 1,
    "accessibility": 1,
    "bestPractices": 1,
    "seo": 1,
    "total": 400
  },
  "firstContentfulPaint": 1017.7080000000001,
  "firstMeaningfulPaint": 1017.7080000000001,
  "speedIndex": 1254.4418280042091,
  "largestContentfulPaint": 1702.97,
  "totalBlockingTime": 0,
  "cumulativeLayoutShift": 0.00011168090502421062,
  "timeToInteractive": 1017.7080000000001,
  "maxPotentialFirstInputDelay": 16,
  "timeToFirstByte": 196.39799999999997,
  "weight": {
    "summary": "6 requests • 170 KiB",
    "total": 174335,
    "image": 6466,
    "imageCount": 1,
    "script": 1564,
    "scriptCount": 1,
    "document": 4779,
    "font": 161526,
    "fontCount": 3,
    "stylesheet": 0,
    "stylesheetCount": 0,
    "thirdParty": 1564,
    "thirdPartyCount": 1
  },
  "run": {
    "number": 1,
    "total": 3
  },
  "sidequests": {
    "-weight.total": 346,
    "+weight.total": 389,
    "-weight.document": 281,
    "+weight.document": 440,
    "-weight.script": 59,
    "+weight.script": 439,
    "-weight.image": 58,
    "+weight.image": 501,
    "-weight.font": 397,
    "+weight.font": 94,
    "+weight.fontCount": 13,
    "-timeToFirstByte": 528,
    "-totalBlockingTime": 1,
    "-largestContentfulPaint": 492
  },
  "axe": {
    "passes": 233,
    "violations": 0
  }
}