{
  "url": "https://thinkdobecreate.com/",
  "requestedUrl": "https://thinkdobecreate.com/",
  "timestamp": 1657594532548,
  "ranks": {
    "hundos": 223,
    "performance": 358,
    "accessibility": 15,
    "cumulative": 215
  },
  "lighthouse": {
    "version": "9.6.1",
    "performance": 0.98,
    "accessibility": 1,
    "bestPractices": 1,
    "seo": 1,
    "total": 398
  },
  "firstContentfulPaint": 996.832,
  "firstMeaningfulPaint": 996.832,
  "speedIndex": 1186.1225279764622,
  "largestContentfulPaint": 1571.143,
  "totalBlockingTime": 0,
  "cumulativeLayoutShift": 0.11599072265625,
  "timeToInteractive": 996.832,
  "maxPotentialFirstInputDelay": 26,
  "timeToFirstByte": 38.78200000000004,
  "weight": {
    "summary": "7 requests • 97 KiB",
    "total": 98881,
    "image": 29585,
    "imageCount": 2,
    "script": 1553,
    "scriptCount": 1,
    "document": 10048,
    "font": 54022,
    "fontCount": 2,
    "stylesheet": 3673,
    "stylesheetCount": 1,
    "thirdParty": 1553,
    "thirdPartyCount": 1
  },
  "run": {
    "number": 1,
    "total": 3
  },
  "sidequests": {
    "-weight.total": 227,
    "+weight.total": 462,
    "-weight.document": 472,
    "+weight.document": 206,
    "-weight.script": 58,
    "+weight.script": 416,
    "-weight.image": 132,
    "+weight.image": 385,
    "-weight.font": 206,
    "+weight.font": 252,
    "+weight.fontCount": 12,
    "-timeToFirstByte": 101,
    "-totalBlockingTime": 1,
    "-largestContentfulPaint": 135
  },
  "axe": {
    "passes": 1175,
    "violations": 0
  }
}